README.txt
setup.cfg
setup.py
docs/HISTORY.txt
raptus/__init__.py
raptus.pfg.tabs.egg-info/PKG-INFO
raptus.pfg.tabs.egg-info/SOURCES.txt
raptus.pfg.tabs.egg-info/dependency_links.txt
raptus.pfg.tabs.egg-info/entry_points.txt
raptus.pfg.tabs.egg-info/namespace_packages.txt
raptus.pfg.tabs.egg-info/not-zip-safe
raptus.pfg.tabs.egg-info/requires.txt
raptus.pfg.tabs.egg-info/top_level.txt
raptus/pfg/__init__.py
raptus/pfg/tabs/__init__.py
raptus/pfg/tabs/configure.zcml
raptus/pfg/tabs/browser/__init__.py
raptus/pfg/tabs/browser/configure.zcml
raptus/pfg/tabs/browser/raptus.pfg.tabs.js
raptus/pfg/tabs/i18n/raptus.pfg.tabs-de.po
raptus/pfg/tabs/i18n/raptus.pfg.tabs.pot
raptus/pfg/tabs/profiles/default/cssregistry.xml
raptus/pfg/tabs/profiles/default/jsregistry.xml
raptus/pfg/tabs/profiles/default/metadata.xml
raptus/pfg/tabs/profiles/default/skins.xml
raptus/pfg/tabs/skins/raptus_pfg_tabs/raptus.pfg.tabs.css.dtml
raptus/pfg/tabs/skins/raptus_pfg_tabs/raptus.pfg.tabs.init.js