Metadata-Version: 1.0
Name: raptus.pfg.tabs
Version: 1.0a2
Summary: Provides a tabbed view of the fieldsets of a form created through PloneFormGen
Home-page: http://raptus.com
Author: Raptus AG
Author-email: dev@raptus.com
License: GPL
Platform: UNKNOWN
Classifier: Programming Language :: Python
Classifier: Topic :: Software Development :: Libraries :: Python Modules
